README.md
setup.py
volk/__init__.py
volk/__main__.py
volk/message.py
volk/volk.py
volk/wsgi.py
volk.egg-info/PKG-INFO
volk.egg-info/SOURCES.txt
volk.egg-info/dependency_links.txt
volk.egg-info/entry_points.txt
volk.egg-info/top_level.txt