Metadata-Version: 2.4
Name: volk
Version: 0.0.4
Summary: WSGI Server
Home-page: https://github.com/joegasewicz/volk
Author: joegasewicz
Author-email: contact@josef.digital
Classifier: Programming Language :: Python :: 3.10
Classifier: Programming Language :: Python :: 3.11
Classifier: Programming Language :: Python :: 3.12
Classifier: License :: OSI Approved :: MIT License
Classifier: Operating System :: OS Independent
Dynamic: author
Dynamic: author-email
Dynamic: classifier
Dynamic: description
Dynamic: description-content-type
Dynamic: home-page
Dynamic: summary
